odoo/addons/stock_picking_progress/README.rst
odoo/addons/stock_picking_progress/__init__.py
odoo/addons/stock_picking_progress/__manifest__.py
odoo/addons/stock_picking_progress/hooks.py
odoo/addons/stock_picking_progress/i18n/stock_picking_progress.pot
odoo/addons/stock_picking_progress/migrations/14.0.1.1.0/post-migrate.py
odoo/addons/stock_picking_progress/migrations/14.0.1.1.0/pre-migrate.py
odoo/addons/stock_picking_progress/migrations/14.0.1.2.0/post-migrate.py
odoo/addons/stock_picking_progress/migrations/14.0.1.2.0/pre-migrate.py
odoo/addons/stock_picking_progress/models/__init__.py
odoo/addons/stock_picking_progress/models/stock_move.py
odoo/addons/stock_picking_progress/models/stock_move_line.py
odoo/addons/stock_picking_progress/models/stock_picking.py
odoo/addons/stock_picking_progress/readme/CONTRIBUTORS.rst
odoo/addons/stock_picking_progress/readme/DESCRIPTION.rst
odoo/addons/stock_picking_progress/static/description/icon.png
odoo/addons/stock_picking_progress/static/description/index.html
odoo/addons/stock_picking_progress/tests/__init__.py
odoo/addons/stock_picking_progress/tests/test_progress.py
odoo/addons/stock_picking_progress/views/stock_picking.xml
odoo14_addon_stock_picking_progress-14.0.1.2.1.dist-info/METADATA
odoo14_addon_stock_picking_progress-14.0.1.2.1.dist-info/WHEEL
odoo14_addon_stock_picking_progress-14.0.1.2.1.dist-info/top_level.txt
odoo14_addon_stock_picking_progress-14.0.1.2.1.dist-info/RECORD
